barbell2pipelines/__init__.py
barbell2pipelines/barbell2pipelines.py
barbell2pipelines-0.2.0.dist-info/LICENSE
barbell2pipelines-0.2.0.dist-info/METADATA
barbell2pipelines-0.2.0.dist-info/WHEEL
barbell2pipelines-0.2.0.dist-info/top_level.txt
barbell2pipelines-0.2.0.dist-info/RECORD
